sentry_wechat
