Metadata-Version: 1.1
Name: sentry-wechat-plugin-renew
Version: 1.0.20.1
Summary: A Sentry extension which integrates with Wechat robot.
Home-page: https://github.com/susujs/sentry-wechat-plugin.git
Author: cxt
Author-email: cxt1122jk@gmail.com
License: BSD
Keywords: sentry wechat
Platform: any
Classifier: Framework :: Django
Classifier: Intended Audience :: Developers
Classifier: Intended Audience :: System Administrators
Classifier: Operating System :: OS Independent
Classifier: Topic :: Software Development
